iterable/__init__.py
iterable/client.py
iterable/exceptions.py
iterable/helpers.py
iterable/resources/__init__.py
iterable/resources/base.py
iterable/resources/campaigns.py
iterable/resources/channels.py
iterable/resources/commerce.py
iterable/resources/email.py
iterable/resources/events.py
iterable/resources/experiments.py
iterable/resources/export.py
iterable/resources/in_app.py
iterable/resources/lists.py
iterable/resources/message_types.py
iterable/resources/metadata.py
iterable/resources/push.py
iterable/resources/sms.py
iterable/resources/templates.py
iterable/resources/users.py
iterable/resources/utils.py
iterable/resources/web_push.py
iterable/resources/workflows.py
iterable_api-0.3.0.dist-info/LICENSE
iterable_api-0.3.0.dist-info/METADATA
iterable_api-0.3.0.dist-info/WHEEL
iterable_api-0.3.0.dist-info/RECORD
