Metadata-Version: 2.3
Name: iterable-api
Version: 0.3.0
Summary: Iterable API wrapper
License: GPL-3.0
Author: Alex Kahn
Author-email: <alexkahn@users.noreply.github.com>
Requires-Python: >=3.6
Classifier: Programming Language :: Python :: 3
Classifier: License :: OSI Approved :: GNU General Public License v3 (GPLv3)
Classifier: Operating System :: OS Independent
Requires-Dist: requests (>=2.26.0)
Project-URL: Bug Tracker, https://github.com/alexkahn/iterable-api/issues
